numdata/__init__.py
numdata/calculate.py
numdataC/__init__.py
numdataC/calculate.py
numdataC-0.0.1.dist-info/LICENSE
numdataC-0.0.1.dist-info/METADATA
numdataC-0.0.1.dist-info/WHEEL
numdataC-0.0.1.dist-info/top_level.txt
numdataC-0.0.1.dist-info/RECORD
