Metadata-Version: 2.1
Name: numdataC
Version: 0.0.1
Summary: A simple package calculating valuews for a simple number
Home-page: UNKNOWN
Author: Charles Chen
Author-email: Charley3chen@gmail.com
License: UNKNOWN
Keywords: package numbers calculations
Platform: UNKNOWN
Classifier: Programming Language :: Python :: 2
Classifier: Operating System :: OS Independent
